Workbook

Sheet Dashboard
A1: DATA TRUST DASHBOARD | N1: Timezone (Last Refresh date)
A2: =IF($D$3="All Domain",ROWS('CDE coverage'!A2:A36),COUNTIF('CDE coverage'!$B$2:$B$36,$D$3))&" rows checked | Trust Score = 40% DQ Score + 20% Glossary + 20% Ownership + 20% Metadata | Set DQ Score (Y/N) on the CDE coverage sheet" | N2: 14 Oct 2026 15:01 (UTC+05:30)
A3: SELECT DOMAIN ▶ | D3: All Domain | H3: ▼ click the yellow cell and pick a domain - the whole dashboard updates
A4: ="TRUST SCORE: "&$D$3 | E4: DQ SCORE | G4: GLOSSARY | I4: OWNERSHIP | K4: METADATA | V4: Table list
A5: =SUMPRODUCT(L15:L18,M15:M18) | E5: =L15 | G5: =L16 | I5: =L17 | K5: =L18 | V5: All Domain
V6: CLAIM
E7: ="weight "&TEXT(M15,"0%") | G7: ="weight "&TEXT(M16,"0%") | I7: ="weight "&TEXT(M17,"0%") | K7: ="weight "&TEXT(M18,"0%") | V7: CLAIM_ASSESSMENT
A8: =IF(A5>=90,"Decision-grade",IF(A5>=75,"Good Trust",IF(A5>=60,"Use with caution","At risk"))) | E8: =J15&" of "&(J15+K15)&" CDEs" | G8: =J16&" of "&(J16+K16)&" CDEs" | I8: =J17&" of "&(J17+K17)&" CDEs" | K8: =J18&" of "&(J18+K18)&" CDEs" | V8: CLAIM_RESERVE
V9: CLAIM_SETTLEMENT
A10: Score bands
A11: 90-100 Decision-grade | D11: 75-89 Good Trust | G11: 60-74 Use with caution | J11: below 60 At risk
A13: Data quality by dimension - table wise | I13: Chart data
A14: Domain | C14: Accuracy | D14: Completeness | E14: Conformity | F14: Uniqueness | G14: Timeliness | I14: Dimension | J14: Trusted | K14: Not Trusted | L14: Coverage % | M14: Weight
A15: CLAIM | C15: =IFERROR(AVERAGEIFS('CDE coverage'!$T$2:$T$36,'CDE coverage'!$B$2:$B$36,$A15),"-") | D15: =IFERROR(AVERAGEIFS('CDE coverage'!$U$2:$U$36,'CDE coverage'!$B$2:$B$36,$A15),"-") | E15: =IFERROR(AVERAGEIFS('CDE coverage'!$V$2:$V$36,'CDE coverage'!$B$2:$B$36,$A15),"-") | F15: =IFERROR(AVERAGEIFS('CDE coverage'!$X$2:$X$36,'CDE coverage'!$B$2:$B$36,$A15),"-") | G15: =IFERROR(IF(AVERAGEIFS('CDE coverage'!$W$2:$W$36,'CDE coverage'!$B$2:$B$36,$A15)>=100,100,0),"-") | I15: DQ Score | J15: =IF($D$3="All Domain",COUNTIF('CDE coverage'!E2:E36,"Y"),COUNTIFS('CDE coverage'!$B$2:$B$36,$D$3,'CDE coverage'!E2:E36,"Y")) | K15: =IF($D$3="All Domain",ROWS('CDE coverage'!A2:A36),COUNTIF('CDE coverage'!$B$2:$B$36,$D$3))-J15 | L15: =IF(J15+K15=0,0,J15/(J15+K15)*100) | M15: ='CDE coverage'!E39
A16: CLAIM_ASSESSMENT | C16: =IFERROR(AVERAGEIFS('CDE coverage'!$T$2:$T$36,'CDE coverage'!$B$2:$B$36,$A16),"-") | D16: =IFERROR(AVERAGEIFS('CDE coverage'!$U$2:$U$36,'CDE coverage'!$B$2:$B$36,$A16),"-") | E16: =IFERROR(AVERAGEIFS('CDE coverage'!$V$2:$V$36,'CDE coverage'!$B$2:$B$36,$A16),"-") | F16: =IFERROR(AVERAGEIFS('CDE coverage'!$X$2:$X$36,'CDE coverage'!$B$2:$B$36,$A16),"-") | G16: =IFERROR(IF(AVERAGEIFS('CDE coverage'!$W$2:$W$36,'CDE coverage'!$B$2:$B$36,$A16)>=100,100,0),"-") | I16: Glossary | J16: =IF($D$3="All Domain",COUNTIF('CDE coverage'!F2:F36,"Y"),COUNTIFS('CDE coverage'!$B$2:$B$36,$D$3,'CDE coverage'!F2:F36,"Y")) | K16: =IF($D$3="All Domain",ROWS('CDE coverage'!A2:A36),COUNTIF('CDE coverage'!$B$2:$B$36,$D$3))-J16 | L16: =IF(J16+K16=0,0,J16/(J16+K16)*100) | M16: ='CDE coverage'!F39
A17: CLAIM_RESERVE | C17: =IFERROR(AVERAGEIFS('CDE coverage'!$T$2:$T$36,'CDE coverage'!$B$2:$B$36,$A17),"-") | D17: =IFERROR(AVERAGEIFS('CDE coverage'!$U$2:$U$36,'CDE coverage'!$B$2:$B$36,$A17),"-") | E17: =IFERROR(AVERAGEIFS('CDE coverage'!$V$2:$V$36,'CDE coverage'!$B$2:$B$36,$A17),"-") | F17: =IFERROR(AVERAGEIFS('CDE coverage'!$X$2:$X$36,'CDE coverage'!$B$2:$B$36,$A17),"-") | G17: =IFERROR(IF(AVERAGEIFS('CDE coverage'!$W$2:$W$36,'CDE coverage'!$B$2:$B$36,$A17)>=100,100,0),"-") | I17: Ownership | J17: =IF($D$3="All Domain",COUNTIF('CDE coverage'!G2:G36,"Y"),COUNTIFS('CDE coverage'!$B$2:$B$36,$D$3,'CDE coverage'!G2:G36,"Y")) | K17: =IF($D$3="All Domain",ROWS('CDE coverage'!A2:A36),COUNTIF('CDE coverage'!$B$2:$B$36,$D$3))-J17 | L17: =IF(J17+K17=0,0,J17/(J17+K17)*100) | M17: ='CDE coverage'!G39
A18: CLAIM_SETTLEMENT | C18: =IFERROR(AVERAGEIFS('CDE coverage'!$T$2:$T$36,'CDE coverage'!$B$2:$B$36,$A18),"-") | D18: =IFERROR(AVERAGEIFS('CDE coverage'!$U$2:$U$36,'CDE coverage'!$B$2:$B$36,$A18),"-") | E18: =IFERROR(AVERAGEIFS('CDE coverage'!$V$2:$V$36,'CDE coverage'!$B$2:$B$36,$A18),"-") | F18: =IFERROR(AVERAGEIFS('CDE coverage'!$X$2:$X$36,'CDE coverage'!$B$2:$B$36,$A18),"-") | G18: =IFERROR(IF(AVERAGEIFS('CDE coverage'!$W$2:$W$36,'CDE coverage'!$B$2:$B$36,$A18)>=100,100,0),"-") | I18: Metadata | J18: =IF($D$3="All Domain",COUNTIF('CDE coverage'!H2:H36,"Y"),COUNTIFS('CDE coverage'!$B$2:$B$36,$D$3,'CDE coverage'!H2:H36,"Y")) | K18: =IF($D$3="All Domain",ROWS('CDE coverage'!A2:A36),COUNTIF('CDE coverage'!$B$2:$B$36,$D$3))-J18 | L18: =IF(J18+K18=0,0,J18/(J18+K18)*100) | M18: ='CDE coverage'!H39
A19: All Domain | C19: =IFERROR(AVERAGE('CDE coverage'!$T$2:$T$36),"-") | D19: =IFERROR(AVERAGE('CDE coverage'!$U$2:$U$36),"-") | E19: =IFERROR(AVERAGE('CDE coverage'!$V$2:$V$36),"-") | F19: =IFERROR(AVERAGE('CDE coverage'!$X$2:$X$36),"-") | G19: =IFERROR(IF(AVERAGE('CDE coverage'!$W$2:$W$36)>=100,100,0),"-")
A21: Timeliness is 100% when the freshness check passes (IS_FRESH = true), 0% when it fails, - when the table has no check.

Sheet CDE coverage
A1: Domain | B1: Table Name | C1: CDE ColumnName | D1: Column Name | E1: DQ Score | F1: Glossary | G1: Ownership | H1: Metadata | I1: DQ Rule Name | J1: DQ Dimension | K1: DQ Rule Score | L1: Domain ID | M1: CDE ID | N1: Glossary ID | O1: Glossary Name | P1: Glossary Status | Q1: Owner ID | R1: Owner Name | S1: Description | T1: DQ Accuracy % | U1: DQ Completeness % | V1: DQ Conformity % | W1: DQ Timeliness % | X1: DQ Uniqueness %
A2: Claims | B2: CLAIM | C2: Claim ID | D2: CLAIM_ID | E2: N | F2: Y | G2: Y | H2: Y | L2: 4f5436b1-84a6-43d8-b7bf-89490196eada | M2: c8c62950-acb2-492b-8b69-7d208c15890d | N2: e5cdc124-e6da-4aa9-8515-37e6ee0ca91b | O2: Claim ID | P2: Published | Q2: fe22eb5f-e472-45c3-8b85-d71c73ea8adc | R2: Srinivasa Dasari | S2: Unique system-generated identifier of a claim. It is the primary key of CLAIM and the foreign key in CLAIM_ASSESSMENT, CLAIM_RESERVE and CLAIM_SETTLEMENT. Critical because it is the join key for the whole model, and orphaned values break the link between a claim and its assessments, reserves and settlements.
A3: Claims | B3: CLAIM | C3: Claim Number | D3: CLAIM_NUMBER | E3: Y | F3: Y | G3: Y | H3: Y | I3: Claim Number is unique | J3: Uniqueness | K3: 97.1% | L3: 4f5436b1-84a6-43d8-b7bf-89490196eada | M3: 0f845d9b-fefb-4677-8de4-638abf1007c6 | N3: 6debf692-6460-4b84-bc99-5bcb201c6ad5 | O3: Claim Number | P3: Published | Q3: fe22eb5f-e472-45c3-8b85-d71c73ea8adc | R3: Srinivasa Dasari | S3: Business identifier of the claim. Critical because duplicates cause double handling and double payment. | X3: 97.1
A4: Claims | B4: CLAIM | C4: Policy Number | D4: POLICY_NUMBER | E4: Y | F4: Y | G4: Y | H4: Y | I4: Policy Number has a valid value | J4: Conformity | K4: 98.6% | L4: 4f5436b1-84a6-43d8-b7bf-89490196eada | M4: 2e84cee1-8e91-412d-8cfc-8eab8de6ad9a | N4: 4009b1d9-0310-420d-b0d1-7aac2a8ddda6 | O4: Policy Number | P4: Published | Q4: fe22eb5f-e472-45c3-8b85-d71c73ea8adc | R4: Srinivasa Dasari | S4: Identifier of the policy the claim is made against. Critical because a wrong value means paying against the wrong coverage. | V4: 98.6
A5: Claims | B5: CLAIM | C5: Claim Type | D5: CLAIM_TYPE | E5: Y | F5: Y | G5: Y | H5: Y | I5: Claim Type has a valid value | J5: Conformity | K5: 99.1% | L5: 4f5436b1-84a6-43d8-b7bf-89490196eada | M5: 145a95e1-e6d0-4f3e-8f54-da3140d12b7b | N5: 670509ab-a947-4255-b90c-750bde935996 | O5: Claim Type | P5: Published | Q5: fe22eb5f-e472-45c3-8b85-d71c73ea8adc | R5: Srinivasa Dasari | S5: Product line or category of the claim. Critical because it drives reserving approach and the regulatory code. | V5: 99.1
A6: Claims | B6: CLAIM | C6: Claim Status | D6: CLAIM_STATUS | E6: N | F6: Y | G6: Y | H6: Y | L6: 4f5436b1-84a6-43d8-b7bf-89490196eada | M6: 3f59ada4-7a9b-4b62-aec6-a013a42cdd99 | N6: 0095a321-199e-4164-ad29-78dc10aa46bc | O6: Claim Status | P6: Published | Q6: fe22eb5f-e472-45c3-8b85-d71c73ea8adc | R6: Srinivasa Dasari | S6: Stage of the claim in its lifecycle. Critical because it drives lifecycle reporting, reserving and settlement eligibility.
A7: Claims | B7: CLAIM | C7: Loss Date | D7: LOSS_DATE | E7: N | F7: Y | G7: Y | H7: Y | L7: 4f5436b1-84a6-43d8-b7bf-89490196eada | M7: ed45bed8-28e9-44dd-abf0-c369a23619e8 | N7: e8e86ff3-81f3-472b-a964-911bb6a38b2d | O7: Loss Date | P7: Published | Q7: fe22eb5f-e472-45c3-8b85-d71c73ea8adc | R7: Srinivasa Dasari | S7: Date the insured event occurred. Critical for coverage validity and late-reporting checks.
A8: Claims | B8: CLAIM | C8: Reported Date | D8: REPORTED_DATE | E8: N | F8: Y | G8: Y | H8: Y | L8: 4f5436b1-84a6-43d8-b7bf-89490196eada | M8: c1a5e2aa-24a9-4e66-b6ef-1c30fe96ebb4 | N8: 6e580308-c39f-4860-a111-1c620a6b8f6f | O8: Reported Date | P8: Published | Q8: fe22eb5f-e472-45c3-8b85-d71c73ea8adc | R8: Srinivasa Dasari | S8: Date the claim was reported to the insurer. Critical for turnaround and SLA measurement.
A9: Claims | B9: CLAIM | C9: Claim Amount Requested | D9: CLAIM_AMOUNT_REQUESTED | E9: N | F9: Y | G9: Y | H9: Y | L9: 4f5436b1-84a6-43d8-b7bf-89490196eada | M9: ac68cdaf-479a-4f57-ac01-c20d1732d368 | N9: 237014ba-8bce-487e-8e04-fd80b8d8482f | O9: Claim Amount Requested | P9: Published | Q9: fe22eb5f-e472-45c3-8b85-d71c73ea8adc | R9: Srinivasa Dasari | S9: Amount the claimant is asking to be paid. Core financial exposure figure.
A10: Claims | B10: CLAIM | C10: Estimated Loss Amount | D10: ESTIMATED_LOSS_AMOUNT | E10: Y | F10: Y | G10: Y | H10: Y | I10: Estimated Loss Amount is filled | J10: Completeness | K10: 99.1% | L10: 4f5436b1-84a6-43d8-b7bf-89490196eada | M10: a8ac98d5-50f3-47d8-ad73-4f1e564d89a9 | N10: e2c9160d-5e9a-46f4-a8a0-bd7cf37a817a | O10: Estimated Loss Amount | P10: Published | Q10: fe22eb5f-e472-45c3-8b85-d71c73ea8adc | R10: Srinivasa Dasari | S10: The insurer's estimate of the total loss, recorded at claim level (CLAIM) and assessment level (CLAIM_ASSESSMENT). Core financial exposure figure; the two values should be governed consistently. | U10: 99.1
A11: Claims | B11: CLAIM | C11: Regulatory Reporting Code | D11: REGULATORY_REPORTING_CODE | E11: N | F11: Y | G11: Y | H11: Y | L11: 4f5436b1-84a6-43d8-b7bf-89490196eada | M11: 0d41bab0-f1a7-4c8a-b83a-c7b32235e537 | N11: 36468f7b-4971-408e-9b89-7a0989004b30 | O11: Regulatory Reporting Code | P11: Published | Q11: fe22eb5f-e472-45c3-8b85-d71c73ea8adc | R11: Srinivasa Dasari | S11: Code that classifies the claim for regulatory reporting. Critical because it determines how the claim appears in regulatory reports.
A12: Claims | B12: CLAIM | C12: Fraud Score | D12: FRAUD_SCORE | E12: N | F12: Y | G12: Y | H12: Y | L12: 4f5436b1-84a6-43d8-b7bf-89490196eada | M12: c993a37a-1659-4628-aef3-7bc6eada45c5 | N12: 0452cc48-73bd-4350-a4c8-54cba1a9437a | O12: Fraud Score | P12: Published | Q12: fe22eb5f-e472-45c3-8b85-d71c73ea8adc | R12: Srinivasa Dasari | S12: Numeric fraud-risk indicator, expected on a 0 to 100 scale, held on both CLAIM and CLAIM_ASSESSMENT. Critical because it feeds fraud-review decisions; the two values should be governed consistently.
A13: Claims | B13: CLAIM | C13: Claim Last Updated Timestamp | D13: UPDATED_TS | E13: Y | F13: Y | G13: Y | H13: Y | I13: CLAIM refreshed daily | J13: Timeliness | K13: 100.0% | L13: 4f5436b1-84a6-43d8-b7bf-89490196eada | M13: 91458b78-efe1-43ee-b7c3-5dfeb93be53b | N13: 4677cc1f-8696-418c-8ccd-f7674a4bbb55 | O13: Claim Last Updated Timestamp | P13: Published | Q13: fe22eb5f-e472-45c3-8b85-d71c73ea8adc | R13: Srinivasa Dasari | S13: The date and time when the claim record was last updated in the source system. | W13: 100
A14: Claims | B14: CLAIM_ASSESSMENT | C14: Claim ID | D14: CLAIM_ID | E14: Y | F14: Y | G14: Y | H14: Y | I14: CLAIM_ID exists in CLAIM | J14: Unspecified | K14: 99.0% | L14: 4f5436b1-84a6-43d8-b7bf-89490196eada | M14: c8c62950-acb2-492b-8b69-7d208c15890d | N14: e5cdc124-e6da-4aa9-8515-37e6ee0ca91b | O14: Claim ID | P14: Published | Q14: fe22eb5f-e472-45c3-8b85-d71c73ea8adc | R14: Srinivasa Dasari | S14: Unique system-generated identifier of a claim. It is the primary key of CLAIM and the foreign key in CLAIM_ASSESSMENT, CLAIM_RESERVE and CLAIM_SETTLEMENT. Critical because it is the join key for the whole model, and orphaned values break the link between a claim and its assessments, reserves and settlements.
A15: Claims | B15: CLAIM_ASSESSMENT | C15: Assessment ID | D15: ASSESSMENT_ID | E15: Y | F15: Y | G15: Y | H15: Y | I15: ASSESSMENT_ID unique | J15: Uniqueness | K15: 100.0% | L15: 4f5436b1-84a6-43d8-b7bf-89490196eada | M15: 5159e534-918a-4899-a1bb-751c73ae3f45 | N15: 17fcbe78-15ff-4c44-856a-e3d851281b44 | O15: Assessment ID | P15: Published | Q15: fe22eb5f-e472-45c3-8b85-d71c73ea8adc | R15: Srinivasa Dasari | S15: Unique system-generated identifier of an assessment. It is the primary key of CLAIM_ASSESSMENT and the optional foreign key in CLAIM_RESERVE. Critical because orphaned values break the link between a reserve and the assessment that justified it. | X15: 100
A16: Claims | B16: CLAIM_ASSESSMENT | C16: Estimated Loss Amount | D16: ESTIMATED_LOSS_AMOUNT | E16: Y | F16: Y | G16: Y | H16: Y | I16: ESTIMATED_LOSS_AMOUNT not blank | J16: Unspecified | K16: 99.0% | L16: 4f5436b1-84a6-43d8-b7bf-89490196eada | M16: a8ac98d5-50f3-47d8-ad73-4f1e564d89a9 | N16: e2c9160d-5e9a-46f4-a8a0-bd7cf37a817a | O16: Estimated Loss Amount | P16: Published | Q16: fe22eb5f-e472-45c3-8b85-d71c73ea8adc | R16: Srinivasa Dasari | S16: The insurer's estimate of the total loss, recorded at claim level (CLAIM) and assessment level (CLAIM_ASSESSMENT). Core financial exposure figure; the two values should be governed consistently.
A17: Claims | B17: CLAIM_ASSESSMENT | C17: Fraud Score | D17: FRAUD_SCORE | E17: Y | F17: Y | G17: Y | H17: Y | I17: FRAUD_SCORE not blank | J17: Unspecified | K17: 98.6% | L17: 4f5436b1-84a6-43d8-b7bf-89490196eada | M17: c993a37a-1659-4628-aef3-7bc6eada45c5 | N17: 0452cc48-73bd-4350-a4c8-54cba1a9437a | O17: Fraud Score | P17: Published | Q17: fe22eb5f-e472-45c3-8b85-d71c73ea8adc | R17: Srinivasa Dasari | S17: Numeric fraud-risk indicator, expected on a 0 to 100 scale, held on both CLAIM and CLAIM_ASSESSMENT. Critical because it feeds fraud-review decisions; the two values should be governed consistently.
A18: Claims | B18: CLAIM_ASSESSMENT | C18: Liability Percentage | D18: LIABILITY_PCT | E18: Y | F18: Y | G18: Y | H18: Y | I18: LIABILITY_PCT not blank | J18: Completeness | K18: 98.7% | L18: 4f5436b1-84a6-43d8-b7bf-89490196eada | M18: 8069cbc5-d9f2-4dbd-a6c6-053830ce669d | N18: 7414a31f-e17e-40a5-a234-a0cf003ffc2f | O18: Liability Percentage | P18: Published | Q18: fe22eb5f-e472-45c3-8b85-d71c73ea8adc | R18: Srinivasa Dasari | S18: Share of the loss for which the insurer is liable, from 0 to 100. Main input to how much is paid. | U18: 98.7
A19: Claims | B19: CLAIM_ASSESSMENT | C19: Damage Estimate | D19: DAMAGE_ESTIMATE | E19: Y | F19: Y | G19: Y | H19: Y | I19: Damage Estimate is filled | J19: Completeness | K19: 98.6% | L19: 4f5436b1-84a6-43d8-b7bf-89490196eada | M19: 57384502-9d3b-49e7-9299-0edbc1ace13a | N19: 082a60d5-9ec8-438b-9ea3-128d28176445 | O19: Damage Estimate | P19: Published | Q19: fe22eb5f-e472-45c3-8b85-d71c73ea8adc | R19: Srinivasa Dasari | S19: Assessor's estimate of the damage or loss found. Main input to reserving and settlement amounts. | U19: 98.6
A20: Claims | B20: CLAIM_ASSESSMENT | C20: Assessment Status | D20: ASSESSMENT_STATUS | E20: Y | F20: Y | G20: Y | H20: Y | I20: Assessment Status has a valid value | J20: Conformity | K20: 98.7% | L20: 4f5436b1-84a6-43d8-b7bf-89490196eada | M20: 3265af8d-bcaa-4769-8a02-148830b51449 | N20: 235d1079-5000-4047-8ae6-93bd4469ad44 | O20: Assessment Status | P20: Published | Q20: fe22eb5f-e472-45c3-8b85-d71c73ea8adc | R20: Srinivasa Dasari | S20: Progress of the assessment. Acts as a control gate before reserving and settlement and must agree with the completed flag. | V20: 98.7
A21: Claims | B21: CLAIM_ASSESSMENT | C21: Assessment Completed Flag | D21: ASSESSMENT_COMPLETED_FLAG | E21: Y | F21: Y | G21: Y | H21: Y | I21: ASSESSMENT_COMPLETED_FLAG allowed values | J21: Conformity | K21: 99.1% | L21: 4f5436b1-84a6-43d8-b7bf-89490196eada | M21: 76e1ff03-ed2d-4206-8344-2aa430ad93ed | N21: 4c8b2d3d-a2d7-4e48-8c8e-b4870cee435b | O21: Assessment Completed Flag | P21: Published | Q21: fe22eb5f-e472-45c3-8b85-d71c73ea8adc | R21: Srinivasa Dasari | S21: Y/N indicator that the assessment is finished (stored as a single character). Control gate that must agree with the assessment status. | V21: 99.1
A22: Claims | B22: CLAIM_RESERVE | C22: Claim ID | D22: CLAIM_ID | E22: N | F22: Y | G22: Y | H22: Y | L22: 4f5436b1-84a6-43d8-b7bf-89490196eada | M22: c8c62950-acb2-492b-8b69-7d208c15890d | N22: e5cdc124-e6da-4aa9-8515-37e6ee0ca91b | O22: Claim ID | P22: Published | Q22: fe22eb5f-e472-45c3-8b85-d71c73ea8adc | R22: Srinivasa Dasari | S22: Unique system-generated identifier of a claim. It is the primary key of CLAIM and the foreign key in CLAIM_ASSESSMENT, CLAIM_RESERVE and CLAIM_SETTLEMENT. Critical because it is the join key for the whole model, and orphaned values break the link between a claim and its assessments, reserves and settlements.
A23: Claims | B23: CLAIM_RESERVE | C23: Assessment ID | D23: ASSESSMENT_ID | E23: N | F23: Y | G23: Y | H23: Y | L23: 4f5436b1-84a6-43d8-b7bf-89490196eada | M23: 5159e534-918a-4899-a1bb-751c73ae3f45 | N23: 17fcbe78-15ff-4c44-856a-e3d851281b44 | O23: Assessment ID | P23: Published | Q23: fe22eb5f-e472-45c3-8b85-d71c73ea8adc | R23: Srinivasa Dasari | S23: Unique system-generated identifier of an assessment. It is the primary key of CLAIM_ASSESSMENT and the optional foreign key in CLAIM_RESERVE. Critical because orphaned values break the link between a reserve and the assessment that justified it.
A24: Claims | B24: CLAIM_RESERVE | C24: Reserve ID | D24: RESERVE_ID | E24: Y | F24: Y | G24: Y | H24: Y | I24: Reserve ID is unique | J24: Uniqueness | K24: 100.0% | L24: 4f5436b1-84a6-43d8-b7bf-89490196eada | M24: 791c448e-f23e-4a24-9404-6e65c400c3db | N24: 2e7776bf-9d7d-4229-963d-6ce4e4a3785e | O24: Reserve ID | P24: Published | Q24: fe22eb5f-e472-45c3-8b85-d71c73ea8adc | R24: Srinivasa Dasari | S24: Unique system-generated identifier of a reserve entry. It is the primary key of CLAIM_RESERVE and the foreign key in CLAIM_SETTLEMENT. Critical because orphaned values leave a settlement with no funding reserve. | X24: 100
A25: Claims | B25: CLAIM_RESERVE | C25: Reserve Amount | D25: RESERVE_AMOUNT | E25: N | F25: Y | G25: Y | H25: Y | L25: 4f5436b1-84a6-43d8-b7bf-89490196eada | M25: 649ce8a2-09e0-49db-951f-d7c600f70de4 | N25: ad9c378b-450b-4f1c-ae2b-5c7ef9b9e47a | O25: Reserve Amount | P25: Published | Q25: fe22eb5f-e472-45c3-8b85-d71c73ea8adc | R25: Srinivasa Dasari | S25: Monetary value set aside for the claim. The most financially significant column; it feeds financial reporting.
A26: Claims | B26: CLAIM_RESERVE | C26: Currency Code | D26: CURRENCY_CODE | E26: Y | F26: Y | G26: Y | H26: Y | I26: Currency Code is filled | J26: Completeness | K26: 100.0% | L26: 4f5436b1-84a6-43d8-b7bf-89490196eada | M26: c662b10d-039b-4047-9a29-d9ad5fbc5cbd | N26: 63c1ae8b-eeb3-403c-b456-eb86b88c8fb3 | O26: Currency Code | P26: Published | Q26: fe22eb5f-e472-45c3-8b85-d71c73ea8adc | R26: Srinivasa Dasari | S26: ISO 4217 currency of the amount (default INR). Without it the reserve amount cannot be interpreted. | U26: 100
A27: Claims | B27: CLAIM_RESERVE | C27: Reserve Status | D27: RESERVE_STATUS | E27: N | F27: Y | G27: Y | H27: Y | L27: 4f5436b1-84a6-43d8-b7bf-89490196eada | M27: b446c222-57fa-47a4-b891-6a9b84961e69 | N27: ebe8a497-6c38-450d-a44c-a214f19cefa2 | O27: Reserve Status | P27: Published | Q27: fe22eb5f-e472-45c3-8b85-d71c73ea8adc | R27: Srinivasa Dasari | S27: State of the reserve (active, adjusted, released). Defines which reserve is in force; errors cause stale or overlapping reserves.
A28: Claims | B28: CLAIM_RESERVE | C28: Reserve Effective From | D28: EFFECTIVE_FROM | E28: N | F28: Y | G28: Y | H28: Y | L28: 4f5436b1-84a6-43d8-b7bf-89490196eada | M28: bb7282d1-cb99-4a24-a287-11e9d1e87696 | N28: bd5b0e1b-92e0-41da-8ca2-eeb187dbf5f8 | O28: Reserve Effective From | P28: Published | Q28: fe22eb5f-e472-45c3-8b85-d71c73ea8adc | R28: Srinivasa Dasari | S28: Start date of the reserve's effective period. Defines which reserve is in force.
A29: Claims | B29: CLAIM_RESERVE | C29: Reserve Effective To | D29: EFFECTIVE_TO | E29: N | F29: Y | G29: Y | H29: Y | L29: 4f5436b1-84a6-43d8-b7bf-89490196eada | M29: 6201ee8c-16d5-4984-bcad-3c0eb554b6f9 | N29: 9ca06d49-cd6c-4cee-bfb1-b25564317567 | O29: Reserve Effective To | P29: Published | Q29: fe22eb5f-e472-45c3-8b85-d71c73ea8adc | R29: Srinivasa Dasari | S29: End date of the reserve's effective period. Empty while the reserve is active; must not precede the start date.
A30: Claims | B30: CLAIM_SETTLEMENT | C30: Claim ID | D30: CLAIM_ID | E30: Y | F30: Y | G30: Y | H30: Y | I30: CLAIM_ID exists in CLAIM | J30: Unspecified | K30: 99.1% | L30: 4f5436b1-84a6-43d8-b7bf-89490196eada | M30: c8c62950-acb2-492b-8b69-7d208c15890d | N30: e5cdc124-e6da-4aa9-8515-37e6ee0ca91b | O30: Claim ID | P30: Published | Q30: fe22eb5f-e472-45c3-8b85-d71c73ea8adc | R30: Srinivasa Dasari | S30: Unique system-generated identifier of a claim. It is the primary key of CLAIM and the foreign key in CLAIM_ASSESSMENT, CLAIM_RESERVE and CLAIM_SETTLEMENT. Critical because it is the join key for the whole model, and orphaned values break the link between a claim and its assessments, reserves and settlements.
A31: Claims | B31: CLAIM_SETTLEMENT | C31: Reserve ID | D31: RESERVE_ID | E31: Y | F31: Y | G31: Y | H31: Y | I31: RESERVE_ID exists in CLAIM_RESERVE | J31: Unspecified | K31: 99.1% | L31: 4f5436b1-84a6-43d8-b7bf-89490196eada | M31: 791c448e-f23e-4a24-9404-6e65c400c3db | N31: 2e7776bf-9d7d-4229-963d-6ce4e4a3785e | O31: Reserve ID | P31: Published | Q31: fe22eb5f-e472-45c3-8b85-d71c73ea8adc | R31: Srinivasa Dasari | S31: Unique system-generated identifier of a reserve entry. It is the primary key of CLAIM_RESERVE and the foreign key in CLAIM_SETTLEMENT. Critical because orphaned values leave a settlement with no funding reserve.
A32: Claims | B32: CLAIM_SETTLEMENT | C32: Approved Settlement Amount | D32: APPROVED_SETTLEMENT_AMOUNT | E32: Y | F32: Y | G32: Y | H32: Y | I32: APPROVED_SETTLEMENT_AMOUNT greater than zero | J32: Accuracy | K32: 98.7% | L32: 4f5436b1-84a6-43d8-b7bf-89490196eada | M32: 8bdbb683-b93d-4d79-8a15-52abb90f4d5e | N32: ad65d3da-bf5f-4d82-9c87-ec37fa409329 | O32: Approved Settlement Amount | P32: Published | Q32: fe22eb5f-e472-45c3-8b85-d71c73ea8adc | R32: Srinivasa Dasari | S32: Amount approved for payment on a settlement. Money actually paid out. | T32: 98.7
A33: Claims | B33: CLAIM_SETTLEMENT | C33: Final Settlement Amount | D33: FINAL_SETTLEMENT_AMOUNT | E33: Y | F33: Y | G33: Y | H33: Y | I33: Final Settlement Amount is filled | J33: Completeness | K33: 98.5% | L33: 4f5436b1-84a6-43d8-b7bf-89490196eada | M33: 3e29f6a4-dad1-40b8-8251-5aa8f34033e1 | N33: 2de2ac80-67c3-4541-8f6e-b5563aa85ccf | O33: Final Settlement Amount | P33: Published | Q33: fe22eb5f-e472-45c3-8b85-d71c73ea8adc | R33: Srinivasa Dasari | S33: Amount finally settled after adjustments; should not exceed the approved amount. Money actually paid out. | U33: 98.5
A34: Claims | B34: CLAIM_SETTLEMENT | C34: Payment Status | D34: PAYMENT_STATUS | E34: Y | F34: Y | G34: Y | H34: Y | I34: PAYMENT_STATUS allowed values | J34: Unspecified | K34: 98.7% | L34: 4f5436b1-84a6-43d8-b7bf-89490196eada | M34: 4e15189b-dba7-451e-97e6-5aab8d7c1179 | N34: e3851bf6-7497-4c59-b126-f1ecf6608d0c | O34: Payment Status | P34: Published | Q34: fe22eb5f-e472-45c3-8b85-d71c73ea8adc | R34: Srinivasa Dasari | S34: State of the payment (initiated, paid, failed, reversed). Shows whether cash has moved.
A35: Claims | B35: CLAIM_SETTLEMENT | C35: Payment Date | D35: PAYMENT_DATE | E35: Y | F35: Y | G35: Y | H35: Y | I35: PAYMENT_DATE within 30 days of SETTLEMENT_DATE | J35: Accuracy | K35: 80.4% | L35: 4f5436b1-84a6-43d8-b7bf-89490196eada | M35: 14ed460a-4010-44c6-b010-66389c04caf2 | N35: 5f449e93-2fca-468f-943f-9aed93b62f5e | O35: Payment Date | P35: Published | Q35: fe22eb5f-e472-45c3-8b85-d71c73ea8adc | R35: Srinivasa Dasari | S35: Date the payment was made. Shows when cash moved; must not precede the settlement date. | T35: 80.4
A36: Claims | B36: CLAIM_SETTLEMENT | C36: Payment Reference | D36: PAYMENT_REFERENCE | E36: Y | F36: Y | G36: Y | H36: Y | I36: Payment Reference is unique | J36: Uniqueness | K36: 75.2% | L36: 4f5436b1-84a6-43d8-b7bf-89490196eada | M36: eb7486f2-2152-4f01-b2ae-f0bab19da373 | N36: 3a7efd70-5dd9-44fb-93fb-15187796f29f | O36: Payment Reference | P36: Published | Q36: fe22eb5f-e472-45c3-8b85-d71c73ea8adc | R36: Srinivasa Dasari | S36: Transaction reference identifying the payment. Lets you trace payments and detect double payments. | X36: 75.2
A38: Coverage % | E38: =COUNTIF(E2:E36,"Y")/ROWS(E2:E36)*100 | F38: =COUNTIF(F2:F36,"Y")/ROWS(F2:F36)*100 | G38: =COUNTIF(G2:G36,"Y")/ROWS(G2:G36)*100 | H38: =COUNTIF(H2:H36,"Y")/ROWS(H2:H36)*100
A39: Weight | E39: 0.4 | F39: 0.2 | G39: 0.2 | H39: 0.2
A40: Trust Score | B40: =SUMPRODUCT(E38:H38,E39:H39)

Sheet DQ Rules
A1: CDE ColumnName - DQ Dimension | B1: Score %
A2: Payment Reference - Uniqueness | B2: 75.2
A3: Payment Date - Accuracy | B3: 80.4
A4: Claim Number - Uniqueness | B4: 97.1
A5: Final Settlement Amount - Completeness | B5: 98.5
A6: Policy Number - Conformity | B6: 98.6
A7: Fraud Score - Unspecified | B7: 98.6
A8: Damage Estimate - Completeness | B8: 98.6
A9: Liability Percentage - Completeness | B9: 98.7
A10: Assessment Status - Conformity | B10: 98.7
A11: Approved Settlement Amount - Accuracy | B11: 98.7
A12: Payment Status - Unspecified | B12: 98.7
A13: Claim ID - Unspecified | B13: 99
... A22: Currency Code - Completeness | B22: 100
